README.txt
setup.py
django_helpers/__init__.py
django_helpers.egg-info/PKG-INFO
django_helpers.egg-info/SOURCES.txt
django_helpers.egg-info/dependency_links.txt
django_helpers.egg-info/not-zip-safe
django_helpers.egg-info/requires.txt
django_helpers.egg-info/top_level.txt
django_helpers/autocomplete/__init__.py
django_helpers/autocomplete/fields.py
django_helpers/autocomplete/urls.py
django_helpers/autocomplete/widgets.py
django_helpers/decorators/__init__.py
django_helpers/email/__init__.py
django_helpers/email/helpers.py
django_helpers/forms/__init__.py
django_helpers/forms/fields.py
django_helpers/forms/helpers.py
django_helpers/forms/widgets.py
django_helpers/middlewares/__init__.py
django_helpers/middlewares/js.py
django_helpers/templatetags/__init__.py
django_helpers/templatetags/get_attr.py
django_helpers/templatetags/helpers.py
django_helpers/templatetags/ignore.py
django_helpers/templatetags/jsmin.py
django_helpers/templatetags/logger.py
django_helpers/templatetags/noop.py
django_helpers/templatetags/noopunquote.py
django_helpers/templatetags/spaceless_include.py
django_helpers/templatetags/variable.py
django_helpers/views/__init__.py
django_helpers/views/curd.py
django_helpers/views/data_table.py
django_helpers/views/helpers.py