Metadata-Version: 1.0
Name: django-helpers
Version: 0.0.1
Summary: Django Helpers and form addons.
Home-page: http://www.xeoscript.com/
Author: Muhammed K K
Author-email: ajumell@gmail.com
License: Freely Distributable
Platform: any
Classifier: Development Status :: 4 - Beta
Classifier: Environment :: Web Environment
Classifier: Framework :: Django
